npycvx/__init__.py
npycvx-0.0.4.dist-info/LICENSE
npycvx-0.0.4.dist-info/METADATA
npycvx-0.0.4.dist-info/WHEEL
npycvx-0.0.4.dist-info/RECORD
