Metadata-Version: 2.1
Name: npycvx
Version: 0.0.4
Summary: Converter from numpy to cvxopt.
License: MIT
Keywords: cvxopt,glpk,solver,ilp,integer linear programming
Author: znittzel
Author-email: rikard@ourstudio.se
Requires-Python: >=3.10
Classifier: License :: OSI Approved :: MIT License
Classifier: Programming Language :: Python :: 3
Classifier: Programming Language :: Python :: 3.10
Classifier: Programming Language :: Python :: 3.11
Classifier: Programming Language :: Python :: 3.12
Requires-Dist: cvxopt (>=1.3.2)
Requires-Dist: numpy (>=2.1.0)
